devtrace/__init__.py
devtrace/commands.py
devtrace/database.py
devtrace/main.py
devtrace/models.py
devtrace/storage.py
devtrace-0.1.1.dist-info/METADATA
devtrace-0.1.1.dist-info/WHEEL
devtrace-0.1.1.dist-info/entry_points.txt
devtrace-0.1.1.dist-info/RECORD
