Metadata-Version: 2.4
Name: devtrace
Version: 0.1.1
Summary: A terminal-based work logger.
Author-email: Satya <satyanarayanprashar73@gmail.com>
Requires-Python: >=3.9
Requires-Dist: pydantic>=2.12.5
Requires-Dist: questionary
Requires-Dist: rich
Requires-Dist: typer[all]
